domolibrary_execution/ConfigInstanceAccount.py
domolibrary_execution/DJ_Workspace.py
domolibrary_execution/DJ_WorkspaceAccount.py
domolibrary_execution/FactoryAccount.py
domolibrary_execution/FactoryAuth.py
domolibrary_execution/FactoryRole.py
domolibrary_execution/FactoryUser.py
domolibrary_execution/__init__.py
domolibrary_execution/_modidx.py
domolibrary_execution/client.py
domolibrary_execution/process.py
domolibrary_execution/LocalAccount/__init__.py
domolibrary_execution/LocalAccount/shortcut_fn.py
domolibrary_execution/client/ExecutionError.py
domolibrary_execution/client/__init__.py
domolibrary_execution/utils/__init__.py
domolibrary_execution/utils/domojupyter.py
domolibrary_execution/utils/factory.py
domolibrary_execution-0.0.123.dist-info/LICENSE
domolibrary_execution-0.0.123.dist-info/METADATA
domolibrary_execution-0.0.123.dist-info/WHEEL
domolibrary_execution-0.0.123.dist-info/entry_points.txt
domolibrary_execution-0.0.123.dist-info/top_level.txt
domolibrary_execution-0.0.123.dist-info/RECORD
