Metadata-Version: 2.1
Name: domolibrary-execution
Version: 0.0.123
Home-page: https://github.com//domolibrary_execution
Author: 
Author-email: 
License: Apache Software License 2.0
Keywords: nbdev jupyter notebook python
Classifier: Development Status :: 4 - Beta
Classifier: Intended Audience :: Developers
Classifier: Natural Language :: English
Classifier: Programming Language :: Python :: 3.8
Classifier: Programming Language :: Python :: 3.9
Classifier: Programming Language :: Python :: 3.10
Classifier: License :: OSI Approved :: Apache Software License
Requires-Python: >=3.8
License-File: LICENSE
Requires-Dist: fastcore
Requires-Dist: pandas
Requires-Dist: domolibrary
Requires-Dist: domolibrary-extensions
Provides-Extra: dev
